trenchfoot/Dockerfile
trenchfoot/README.md
trenchfoot/__init__.py
trenchfoot/generate_scenarios.py
trenchfoot/gmsh_sloped_trench_mesher.py
trenchfoot/plot_mesh.py
trenchfoot/render_colors.py
trenchfoot/scene_spec_example.json
trenchfoot/trench_scene_generator_v3.py
trenchfoot/scenarios/SUMMARY.json
trenchfoot/scenarios/S01_straight_vwalls/ground_truth_isosurface.html
trenchfoot/scenarios/S01_straight_vwalls/metrics.json
trenchfoot/scenarios/S01_straight_vwalls/preview.png
trenchfoot/scenarios/S01_straight_vwalls/preview_oblique.png
trenchfoot/scenarios/S01_straight_vwalls/preview_side.png
trenchfoot/scenarios/S01_straight_vwalls/preview_top.png
trenchfoot/scenarios/S01_straight_vwalls/scene.json
trenchfoot/scenarios/S01_straight_vwalls/sdf_metadata.json
trenchfoot/scenarios/S01_straight_vwalls/trench_scene.obj
trenchfoot/scenarios/S01_straight_vwalls/meshes/trench_scene_culled.obj
trenchfoot/scenarios/S01_straight_vwalls/point_clouds/culled/resolution0p050.pth
trenchfoot/scenarios/S01_straight_vwalls/point_clouds/full/resolution0p050.pth
trenchfoot/scenarios/S01_straight_vwalls/volumetric/trench_volume.msh
trenchfoot/scenarios/S02_straight_slope_pipe/ground_truth_isosurface.html
trenchfoot/scenarios/S02_straight_slope_pipe/metrics.json
trenchfoot/scenarios/S02_straight_slope_pipe/preview.png
trenchfoot/scenarios/S02_straight_slope_pipe/preview_oblique.png
trenchfoot/scenarios/S02_straight_slope_pipe/preview_side.png
trenchfoot/scenarios/S02_straight_slope_pipe/preview_top.png
trenchfoot/scenarios/S02_straight_slope_pipe/scene.json
trenchfoot/scenarios/S02_straight_slope_pipe/sdf_metadata.json
trenchfoot/scenarios/S02_straight_slope_pipe/trench_scene.obj
trenchfoot/scenarios/S02_straight_slope_pipe/meshes/trench_scene_culled.obj
trenchfoot/scenarios/S02_straight_slope_pipe/point_clouds/culled/resolution0p050.pth
trenchfoot/scenarios/S02_straight_slope_pipe/point_clouds/full/resolution0p050.pth
trenchfoot/scenarios/S02_straight_slope_pipe/volumetric/trench_volume.msh
trenchfoot-0.4.3.dist-info/METADATA
trenchfoot-0.4.3.dist-info/WHEEL
trenchfoot-0.4.3.dist-info/entry_points.txt
trenchfoot-0.4.3.dist-info/licenses/LICENSE
trenchfoot-0.4.3.dist-info/RECORD
