Metadata-Version: 2.4
Name: trenchfoot
Version: 0.4.3
Summary: Synthetic trench scenario generator bundle (surfaces + volumetrics).
Author: Liam Moore
License-File: LICENSE
Requires-Python: >=3.12
Requires-Dist: numpy>=1.26
Provides-Extra: dev
Requires-Dist: pytest>=8.3; extra == 'dev'
Provides-Extra: mesher
Requires-Dist: gmsh>=4.11; extra == 'mesher'
Provides-Extra: preview
Requires-Dist: matplotlib>=3.8; extra == 'preview'
Provides-Extra: viz
Requires-Dist: plotly>=5.24; extra == 'viz'
